ovos_persona/__init__.py
ovos_persona/hpm.py
ovos_persona/solvers.py
ovos_persona/version.py
ovos_persona/locale/ca/Release.voc
ovos_persona/locale/ca/activated_persona.dialog
ovos_persona/locale/ca/active_persona.dialog
ovos_persona/locale/ca/active_persona.intent
ovos_persona/locale/ca/ask.intent
ovos_persona/locale/ca/list_personas.dialog
ovos_persona/locale/ca/list_personas.intent
ovos_persona/locale/ca/no_active_persona.dialog
ovos_persona/locale/ca/no_personas.dialog
ovos_persona/locale/ca/persona_error.dialog
ovos_persona/locale/ca/persona_select.dialog
ovos_persona/locale/ca/release_persona.dialog
ovos_persona/locale/ca/summon.intent
ovos_persona/locale/ca/unknown_persona.dialog
ovos_persona/locale/da/Release.voc
ovos_persona/locale/da/activated_persona.dialog
ovos_persona/locale/da/active_persona.dialog
ovos_persona/locale/da/active_persona.intent
ovos_persona/locale/da/ask.intent
ovos_persona/locale/da/list_personas.dialog
ovos_persona/locale/da/list_personas.intent
ovos_persona/locale/da/no_active_persona.dialog
ovos_persona/locale/da/no_personas.dialog
ovos_persona/locale/da/persona_error.dialog
ovos_persona/locale/da/persona_select.dialog
ovos_persona/locale/da/release_persona.dialog
ovos_persona/locale/da/summon.intent
ovos_persona/locale/da/unknown_persona.dialog
ovos_persona/locale/de/Release.voc
ovos_persona/locale/de/activated_persona.dialog
ovos_persona/locale/de/active_persona.dialog
ovos_persona/locale/de/active_persona.intent
ovos_persona/locale/de/ask.intent
ovos_persona/locale/de/ask.voc
ovos_persona/locale/de/list_personas.dialog
ovos_persona/locale/de/list_personas.intent
ovos_persona/locale/de/no_active_persona.dialog
ovos_persona/locale/de/no_personas.dialog
ovos_persona/locale/de/opinion.voc
ovos_persona/locale/de/persona.voc
ovos_persona/locale/de/persona_error.dialog
ovos_persona/locale/de/persona_select.dialog
ovos_persona/locale/de/release_persona.dialog
ovos_persona/locale/de/summon.intent
ovos_persona/locale/de/summon.voc
ovos_persona-0.6.24.dist-info/licenses/LICENSE
ovos_persona-0.6.24.dist-info/METADATA
ovos_persona-0.6.24.dist-info/WHEEL
ovos_persona-0.6.24.dist-info/entry_points.txt
ovos_persona-0.6.24.dist-info/top_level.txt
ovos_persona-0.6.24.dist-info/zip-safe
ovos_persona-0.6.24.dist-info/RECORD
