Metadata-Version: 2.4
Name: ovos_persona
Version: 0.6.24
Summary: persona pipeline for ovos
Home-page: https://github.com/OpenVoiceOS/ovos-persona
Author: jarbasai
Author-email: jarbasai@mailfence.com
License: Apache License 2.0
License-File: LICENSE
Requires-Dist: ovos-plugin-manager<3.0.0,>=0.8.3
Requires-Dist: ovos-openai-plugin<3.0.0,>=2.0.0
Requires-Dist: ovos-solver-failure-plugin
Requires-Dist: ovos-utils<1.0.0,>=0.8.0a1
Requires-Dist: langcodes
Dynamic: author
Dynamic: author-email
Dynamic: description
Dynamic: description-content-type
Dynamic: home-page
Dynamic: license
Dynamic: license-file
Dynamic: requires-dist
Dynamic: summary
